Punctuator/Punctuator.py
Punctuator/__init__.py
Punctuator/test.py
Punctuator/utils.py
TextPunctuator-1.0.5.dist-info/METADATA
TextPunctuator-1.0.5.dist-info/WHEEL
TextPunctuator-1.0.5.dist-info/top_level.txt
TextPunctuator-1.0.5.dist-info/RECORD
