Metadata-Version: 2.1
Name: TextPunctuator
Version: 1.0.5
Summary: A package to punctuate text, currently supporting French text, more languages comming soon.
Home-page: https://github.com/rouzki/TextPunctuator
Author: Zakarya ROUZKI
Author-email: zakaryarouzki@gmail.com
License: UNKNOWN
Keywords: punctuator,nlp,text,transformers,t5
Platform: UNKNOWN
Classifier: Intended Audience :: Science/Research
Classifier: License :: OSI Approved :: MIT License
Classifier: Programming Language :: Python :: 3
Classifier: Topic :: Scientific/Engineering :: Artificial Intelligence
Requires-Python: >=3.6
Requires-Dist: transformers
Requires-Dist: langdetect
